{"title":"The Dick Fairy.mp4","uid":13500168,"size":397940752,"categoryP":"porn","categoryS":"movie_clips","magnet":"?xt=urn:btih:067312b5627befe8ab45c467ead2ed3d59e0e804&amp;dn=The+Dick+Fairy.mp4&amp;tr=udp%3A%2F%2Ftracker.leechers-paradise.org%3A6969&amp;tr=udp%3A%2F%2Fzer0day.ch%3A1337&amp;tr=udp%3A%2F%2Fopen.demonii.com%3A1337&amp;tr=udp%3A%2F%2Ftracker.coppersurfer.tk%3A6969&amp;tr=udp%3A%2F%2Fexodus.desync.com%3A6969","seeders":0,"leechers":0,"uploader":"Piratepr0n","files":1,"time":1455191832,"description":"-------------------------------------------------------------------------------------\nName:\nThe Dick Fairy.mp4\n-------------------------------------------------------------------------------------\nFile list:\nThe Dick Fairy.mp4 (380 MiB | 854x480 | 44min 45s | MPEG-4) \nhttp://imgfapper.com/img-56bc6902569c1.html","torrent":{"xt":"urn:btih:067312b5627befe8ab45c467ead2ed3d59e0e804","amp;dn":"The+Dick+Fairy.mp4","amp;tr":["udp%3A%2F%2Ftracker.leechers-paradise.org%3A6969","udp%3A%2F%2Fzer0day.ch%3A1337","udp%3A%2F%2Fopen.demonii.com%3A1337","udp%3A%2F%2Ftracker.coppersurfer.tk%3A6969","udp%3A%2F%2Fexodus.desync.com%3A6969"],"infoHash":"067312b5627befe8ab45c467ead2ed3d59e0e804","infoHashBuffer":{"type":"Buffer","data":[6,115,18,181,98,123,239,232,171,69,196,103,234,210,237,61,89,224,232,4]},"announce":[],"urlList":[]}}