{"title":"Anal Dominican Teen","uid":14422040,"size":97959194,"categoryP":"porn","categoryS":"movie_clips","magnet":"?xt=urn:btih:0bf381f2812269492fbcaf660d68d346862a2ce9&amp;dn=Anal+Dominican+Teen&amp;tr=udp%3A%2F%2Ftracker.leechers-paradise.org%3A6969&amp;tr=udp%3A%2F%2Fzer0day.ch%3A1337&amp;tr=udp%3A%2F%2Fopen.demonii.com%3A1337&amp;tr=udp%3A%2F%2Ftracker.coppersurfer.tk%3A6969&amp;tr=udp%3A%2F%2Fexodus.desync.com%3A6969","seeders":0,"leechers":1,"uploader":"demonoidt","files":5,"time":1461543411,"description":"Samples\r\n \nhttp://adultwallpapers.co.in/anal-dominican-teen/\r\n \nhttp://demonoid.co/2016/04/24/anal-dominican-teen/","torrent":{"xt":"urn:btih:0bf381f2812269492fbcaf660d68d346862a2ce9","amp;dn":"Anal+Dominican+Teen","amp;tr":["udp%3A%2F%2Ftracker.leechers-paradise.org%3A6969","udp%3A%2F%2Fzer0day.ch%3A1337","udp%3A%2F%2Fopen.demonii.com%3A1337","udp%3A%2F%2Ftracker.coppersurfer.tk%3A6969","udp%3A%2F%2Fexodus.desync.com%3A6969"],"infoHash":"0bf381f2812269492fbcaf660d68d346862a2ce9","infoHashBuffer":{"type":"Buffer","data":[11,243,129,242,129,34,105,73,47,188,175,102,13,104,211,70,134,42,44,233]},"announce":[],"urlList":[]}}