{"title":"{EvilAngel} Francesca Le, Anikka Albrite - Anal Royalty, Scene 1","uid":14394989,"size":2762933960,"categoryP":"porn","categoryS":"hd___movies","magnet":"?xt=urn:btih:13e8ed84e8fdb3c0558a2e9776d90c5a14d2b826&amp;dn=%7BEvilAngel%7D+Francesca+Le%2C+Anikka+Albrite+-+Anal+Royalty%2C+Scene+1&amp;tr=udp%3A%2F%2Ftracker.leechers-paradise.org%3A6969&amp;tr=udp%3A%2F%2Fzer0day.ch%3A1337&amp;tr=udp%3A%2F%2Fopen.demonii.com%3A1337&amp;tr=udp%3A%2F%2Ftracker.coppersurfer.tk%3A6969&amp;tr=udp%3A%2F%2Fexodus.desync.com%3A6969","seeders":0,"leechers":1,"uploader":"porn4u","files":1,"time":1461337264,"description":"{EvilAngel} Francesca Le, Anikka Albrite - Anal Royalty, Scene 1 (22 April 2016) 1080p\r\n\r\n\r\nscreenshot\r\n \nhttp://imgdone.com/viewer.php?file=93063546913680466973.jpg\r\n\r\n\r\nGeneral info:\r\n\r\n\r\nSize: 2634 Mb,\r\nDuration: 00: 52: 29,\r\nStreams: 2,\r\nFull bitrate: 7017 kb/s\r\nVideo: H264 (avc1), 1920x1080, 29.97 fps\r\nAudio: AAC, STEREO, 44.1 kHz, 192 kb/s\r\n\r\nBodacious, butt-blessed blonde Anikka Albrite shares a wicked anal threesome with married swingers Francesca Le and Mark Wood. Anikka's greased ass sways hypnotically and a glass toy opens her sphincter. Mark nails Anikka's bush-topped pussy; spit flows as she practices deep throating. Buxom MILF Francesca eats pussy, rims Anikka and enjoys fragrant smothering as the blonde sits on her face. Anikka's bunghole consumes cock while Francesca licks balls. Francesca chokes and masturbates Anikka; she sucks Mark ass-to-mouth as Anikka sits on his face. Francesca tugs Anikka's face up her ass for a rim job. The ladies share a creamy kiss","torrent":{"xt":"urn:btih:13e8ed84e8fdb3c0558a2e9776d90c5a14d2b826","amp;dn":"%7BEvilAngel%7D+Francesca+Le%2C+Anikka+Albrite+-+Anal+Royalty%2C+Scene+1","amp;tr":["udp%3A%2F%2Ftracker.leechers-paradise.org%3A6969","udp%3A%2F%2Fzer0day.ch%3A1337","udp%3A%2F%2Fopen.demonii.com%3A1337","udp%3A%2F%2Ftracker.coppersurfer.tk%3A6969","udp%3A%2F%2Fexodus.desync.com%3A6969"],"infoHash":"13e8ed84e8fdb3c0558a2e9776d90c5a14d2b826","infoHashBuffer":{"type":"Buffer","data":[19,232,237,132,232,253,179,192,85,138,46,151,118,217,12,90,20,210,184,38]},"announce":[],"urlList":[]}}