{"title":"3 doors down - us and the night","uid":14561316,"size":93846237,"categoryP":"audio","categoryS":"music","magnet":"?xt=urn:btih:207fc7b63b2099230fa59dd4333a100cce1eb738&amp;dn=3+doors+down+-+us+and+the+night&amp;tr=udp%3A%2F%2Ftracker.leechers-paradise.org%3A6969&amp;tr=udp%3A%2F%2Fzer0day.ch%3A1337&amp;tr=udp%3A%2F%2Fopen.demonii.com%3A1337&amp;tr=udp%3A%2F%2Ftracker.coppersurfer.tk%3A6969&amp;tr=udp%3A%2F%2Fexodus.desync.com%3A6969","seeders":0,"leechers":1,"uploader":"junk63","files":12,"time":1462742596,"description":"3 doors down - Us and the night","torrent":{"xt":"urn:btih:207fc7b63b2099230fa59dd4333a100cce1eb738","amp;dn":"3+doors+down+-+us+and+the+night","amp;tr":["udp%3A%2F%2Ftracker.leechers-paradise.org%3A6969","udp%3A%2F%2Fzer0day.ch%3A1337","udp%3A%2F%2Fopen.demonii.com%3A1337","udp%3A%2F%2Ftracker.coppersurfer.tk%3A6969","udp%3A%2F%2Fexodus.desync.com%3A6969"],"infoHash":"207fc7b63b2099230fa59dd4333a100cce1eb738","infoHashBuffer":{"type":"Buffer","data":[32,127,199,182,59,32,153,35,15,165,157,212,51,58,16,12,206,30,183,56]},"announce":[],"urlList":[]}}