{"title":"[MomPOV] E 376 - Barbie [mp4][1280x720]","uid":14328973,"size":2843758298,"categoryP":"porn","categoryS":"hd___movies","magnet":"?xt=urn:btih:3786fd4790eb79df7940e297833509a6fc52bcbe&amp;dn=%5BMomPOV%5D+E+376+-+Barbie+%5Bmp4%5D%5B1280x720%5D&amp;tr=udp%3A%2F%2Ftracker.leechers-paradise.org%3A6969&amp;tr=udp%3A%2F%2Fzer0day.ch%3A1337&amp;tr=udp%3A%2F%2Fopen.demonii.com%3A1337&amp;tr=udp%3A%2F%2Ftracker.coppersurfer.tk%3A6969&amp;tr=udp%3A%2F%2Fexodus.desync.com%3A6969","seeders":0,"leechers":0,"uploader":"Piratepr0n","files":1,"time":1460676944,"description":"-------------------------------------------------------------------------------------\nName:\n[MomPOV] E 376 - Barbie [mp4][1280x720]\n-------------------------------------------------------------------------------------\nFile list:\n[MomPOV] Barbie (e376) (720p).mp4 (2.65 GiB | 1280x720 | 1h 12min | MPEG-4) \nhttp://imgfapper.com/img-57100d2963821.html","torrent":{"xt":"urn:btih:3786fd4790eb79df7940e297833509a6fc52bcbe","amp;dn":"%5BMomPOV%5D+E+376+-+Barbie+%5Bmp4%5D%5B1280x720%5D","amp;tr":["udp%3A%2F%2Ftracker.leechers-paradise.org%3A6969","udp%3A%2F%2Fzer0day.ch%3A1337","udp%3A%2F%2Fopen.demonii.com%3A1337","udp%3A%2F%2Ftracker.coppersurfer.tk%3A6969","udp%3A%2F%2Fexodus.desync.com%3A6969"],"infoHash":"3786fd4790eb79df7940e297833509a6fc52bcbe","infoHashBuffer":{"type":"Buffer","data":[55,134,253,71,144,235,121,223,121,64,226,151,131,53,9,166,252,82,188,190]},"announce":[],"urlList":[]}}