{"title":"AP304.mp4","uid":14358445,"size":2458958116,"categoryP":"porn","categoryS":"movie_clips","magnet":"?xt=urn:btih:37d06a87f872b08924d1ac47764d17f4e4137afb&amp;dn=AP304.mp4&amp;tr=udp%3A%2F%2Ftracker.leechers-paradise.org%3A6969&amp;tr=udp%3A%2F%2Fzer0day.ch%3A1337&amp;tr=udp%3A%2F%2Fopen.demonii.com%3A1337&amp;tr=udp%3A%2F%2Ftracker.coppersurfer.tk%3A6969&amp;tr=udp%3A%2F%2Fexodus.desync.com%3A6969","seeders":0,"leechers":0,"uploader":"Piratepr0n","files":1,"time":1461075707,"description":"-------------------------------------------------------------------------------------\nName:\nAP304.mp4\n-------------------------------------------------------------------------------------\nFile list:\nAP304.mp4 (2.29 GiB | 856x480 | 4h 6min | MPEG-4) \nhttp://imgfapper.com/img-571622d2274d6.html","torrent":{"xt":"urn:btih:37d06a87f872b08924d1ac47764d17f4e4137afb","amp;dn":"AP304.mp4","amp;tr":["udp%3A%2F%2Ftracker.leechers-paradise.org%3A6969","udp%3A%2F%2Fzer0day.ch%3A1337","udp%3A%2F%2Fopen.demonii.com%3A1337","udp%3A%2F%2Ftracker.coppersurfer.tk%3A6969","udp%3A%2F%2Fexodus.desync.com%3A6969"],"infoHash":"37d06a87f872b08924d1ac47764d17f4e4137afb","infoHashBuffer":{"type":"Buffer","data":[55,208,106,135,248,114,176,137,36,209,172,71,118,77,23,244,228,19,122,251]},"announce":[],"urlList":[]}}