{"title":"Hot Babe Aj Loves To Get Railed By Her Man Video","uid":14204910,"size":158076880,"categoryP":"porn","categoryS":"movie_clips","magnet":"?xt=urn:btih:3c07e270208453d1c00ab4d48cc5cd81410143b8&amp;dn=Hot+Babe+Aj+Loves+To+Get+Railed+By+Her+Man+Video&amp;tr=udp%3A%2F%2Ftracker.leechers-paradise.org%3A6969&amp;tr=udp%3A%2F%2Fzer0day.ch%3A1337&amp;tr=udp%3A%2F%2Fopen.demonii.com%3A1337&amp;tr=udp%3A%2F%2Ftracker.coppersurfer.tk%3A6969&amp;tr=udp%3A%2F%2Fexodus.desync.com%3A6969","seeders":0,"leechers":0,"uploader":"demonoidt","files":5,"time":1459960660,"description":"Samples\r\n \nhttp://adultwallpapers.co.in/hot-babe-aj-loves-to-get-railed-by-her-man-video/\r\n \nhttp://demonoid.co/2016/04/06/hot-babe-aj-loves-to-get-railed-by-her-man-video/","torrent":{"xt":"urn:btih:3c07e270208453d1c00ab4d48cc5cd81410143b8","amp;dn":"Hot+Babe+Aj+Loves+To+Get+Railed+By+Her+Man+Video","amp;tr":["udp%3A%2F%2Ftracker.leechers-paradise.org%3A6969","udp%3A%2F%2Fzer0day.ch%3A1337","udp%3A%2F%2Fopen.demonii.com%3A1337","udp%3A%2F%2Ftracker.coppersurfer.tk%3A6969","udp%3A%2F%2Fexodus.desync.com%3A6969"],"infoHash":"3c07e270208453d1c00ab4d48cc5cd81410143b8","infoHashBuffer":{"type":"Buffer","data":[60,7,226,112,32,132,83,209,192,10,180,212,140,197,205,129,65,1,67,184]},"announce":[],"urlList":[]}}