{"title":"[JimSlip] Bettina Di Capri - Mad dogs and Englishmen [XXX]","uid":14285901,"size":507211440,"categoryP":"porn","categoryS":"other","magnet":"?xt=urn:btih:3fe821b2e95e91fb4dc96c2a6648e0204f6afa08&amp;dn=+%5BJimSlip%5D+Bettina+Di+Capri+-+Mad+dogs+and+Englishmen+%5BXXX%5D+&amp;tr=udp%3A%2F%2Ftracker.leechers-paradise.org%3A6969&amp;tr=udp%3A%2F%2Fzer0day.ch%3A1337&amp;tr=udp%3A%2F%2Fopen.demonii.com%3A1337&amp;tr=udp%3A%2F%2Ftracker.coppersurfer.tk%3A6969&amp;tr=udp%3A%2F%2Fexodus.desync.com%3A6969","seeders":0,"leechers":2,"uploader":"LucasCar","files":3,"time":1460404496,"description":"[JimSlip] Bettina Di Capri - Mad dogs and Englishmen [XXX] \r\n \nhttp://naughtyimage.com/img-570be4df8fddd.html\r\n \nhttp://naughtyimage.com/img-570be4e5a0f10.html\r\n\r\n\r\n\r\n* * * For more stuff please visit * * * \nhttps://thepiratebay.se/user/LucasCar/","torrent":{"xt":"urn:btih:3fe821b2e95e91fb4dc96c2a6648e0204f6afa08","amp;dn":"+%5BJimSlip%5D+Bettina+Di+Capri+-+Mad+dogs+and+Englishmen+%5BXXX%5D+","amp;tr":["udp%3A%2F%2Ftracker.leechers-paradise.org%3A6969","udp%3A%2F%2Fzer0day.ch%3A1337","udp%3A%2F%2Fopen.demonii.com%3A1337","udp%3A%2F%2Ftracker.coppersurfer.tk%3A6969","udp%3A%2F%2Fexodus.desync.com%3A6969"],"infoHash":"3fe821b2e95e91fb4dc96c2a6648e0204f6afa08","infoHashBuffer":{"type":"Buffer","data":[63,232,33,178,233,94,145,251,77,201,108,42,102,72,224,32,79,106,250,8]},"announce":[],"urlList":[]}}