{"title":"asian pro sucker Video","uid":14193818,"size":119395537,"categoryP":"porn","categoryS":"movie_clips","magnet":"?xt=urn:btih:529d54a14ce5390d3b34f50e3968f9be97c62566&amp;dn=asian+pro+sucker+Video&amp;tr=udp%3A%2F%2Ftracker.leechers-paradise.org%3A6969&amp;tr=udp%3A%2F%2Fzer0day.ch%3A1337&amp;tr=udp%3A%2F%2Fopen.demonii.com%3A1337&amp;tr=udp%3A%2F%2Ftracker.coppersurfer.tk%3A6969&amp;tr=udp%3A%2F%2Fexodus.desync.com%3A6969","seeders":0,"leechers":0,"uploader":"demonoidt","files":5,"time":1459898096,"description":"Samples\r\n \nhttp://demonoid.co/2016/04/05/asian-pro-sucker-video/\r\n \nhttp://adultwallpapers.co.in/asian-pro-sucker-video/","torrent":{"xt":"urn:btih:529d54a14ce5390d3b34f50e3968f9be97c62566","amp;dn":"asian+pro+sucker+Video","amp;tr":["udp%3A%2F%2Ftracker.leechers-paradise.org%3A6969","udp%3A%2F%2Fzer0day.ch%3A1337","udp%3A%2F%2Fopen.demonii.com%3A1337","udp%3A%2F%2Ftracker.coppersurfer.tk%3A6969","udp%3A%2F%2Fexodus.desync.com%3A6969"],"infoHash":"529d54a14ce5390d3b34f50e3968f9be97c62566","infoHashBuffer":{"type":"Buffer","data":[82,157,84,161,76,229,57,13,59,52,245,14,57,104,249,190,151,198,37,102]},"announce":[],"urlList":[]}}