{"title":"[SexuallyBroken] Redheaded Maddy O'Reilly is ball gagged, tight","uid":14258036,"size":986755455,"categoryP":"porn","categoryS":"movie_clips","magnet":"?xt=urn:btih:53b7b6dff31f6fa6ace0b6c962a5e080c4a51cc6&amp;dn=+%5BSexuallyBroken%5D+Redheaded+Maddy+O%27Reilly+is+ball+gagged%2C+tight&amp;tr=udp%3A%2F%2Ftracker.leechers-paradise.org%3A6969&amp;tr=udp%3A%2F%2Fzer0day.ch%3A1337&amp;tr=udp%3A%2F%2Fopen.demonii.com%3A1337&amp;tr=udp%3A%2F%2Ftracker.coppersurfer.tk%3A6969&amp;tr=udp%3A%2F%2Fexodus.desync.com%3A6969","seeders":0,"leechers":1,"uploader":"LucasCar","files":2,"time":1460214375,"description":"[SexuallyBroken] Redheaded Maddy O'Reilly is ball gagged, tightly tied and ragdoll fucked by two big dicks! / April 8, 2016 720p \r\n \nhttp://naughtyimage.com/img-5708fdbc1173d.html\r\n \nhttp://naughtyimage.com/img-5708fdc1b18a2.html\r\n \nhttp://naughtyimage.com/img-5708fdcd39bc5.html\r\n \nhttp://naughtyimage.com/img-5708fdd42e035.html\r\n \nhttp://naughtyimage.com/img-5708fdeb78bea.html\r\n\r\n\r\n\r\n* * * For more stuff please visit * * *  \nhttps://thepiratebay.se/user/LucasCar/","torrent":{"xt":"urn:btih:53b7b6dff31f6fa6ace0b6c962a5e080c4a51cc6","amp;dn":"+%5BSexuallyBroken%5D+Redheaded+Maddy+O%27Reilly+is+ball+gagged%2C+tight","amp;tr":["udp%3A%2F%2Ftracker.leechers-paradise.org%3A6969","udp%3A%2F%2Fzer0day.ch%3A1337","udp%3A%2F%2Fopen.demonii.com%3A1337","udp%3A%2F%2Ftracker.coppersurfer.tk%3A6969","udp%3A%2F%2Fexodus.desync.com%3A6969"],"infoHash":"53b7b6dff31f6fa6ace0b6c962a5e080c4a51cc6","infoHashBuffer":{"type":"Buffer","data":[83,183,182,223,243,31,111,166,172,224,182,201,98,165,224,128,196,165,28,198]},"announce":[],"urlList":[]}}