{"title":"Seth.Meyers.2016.02.15.Jason.Sudeikis.XviD-AFG","uid":13574988,"size":557655529,"categoryP":"video","categoryS":"tv_shows","magnet":"?xt=urn:btih:58f453b3705e6cc5e772e4f394c811b2f6c6e453&amp;dn=Seth.Meyers.2016.02.15.Jason.Sudeikis.XviD-AFG&amp;tr=udp%3A%2F%2Ftracker.leechers-paradise.org%3A6969&amp;tr=udp%3A%2F%2Fzer0day.ch%3A1337&amp;tr=udp%3A%2F%2Fopen.demonii.com%3A1337&amp;tr=udp%3A%2F%2Ftracker.coppersurfer.tk%3A6969&amp;tr=udp%3A%2F%2Fexodus.desync.com%3A6969","seeders":0,"leechers":0,"uploader":"TvTeam","files":12,"time":1455700866,"description":"https://www.torrenting.com\r\n\r\nSign up is OPEN - for time being. Come and have fun.\r\n\r\n------------------------------------------------------------------------\r\n\r\nReNEW our seedbox by donating bitcoin To: 1N1qWp6Hk1REFXgJ8yviqCnLsn76BfXFh1","torrent":{"xt":"urn:btih:58f453b3705e6cc5e772e4f394c811b2f6c6e453","amp;dn":"Seth.Meyers.2016.02.15.Jason.Sudeikis.XviD-AFG","amp;tr":["udp%3A%2F%2Ftracker.leechers-paradise.org%3A6969","udp%3A%2F%2Fzer0day.ch%3A1337","udp%3A%2F%2Fopen.demonii.com%3A1337","udp%3A%2F%2Ftracker.coppersurfer.tk%3A6969","udp%3A%2F%2Fexodus.desync.com%3A6969"],"infoHash":"58f453b3705e6cc5e772e4f394c811b2f6c6e453","infoHashBuffer":{"type":"Buffer","data":[88,244,83,179,112,94,108,197,231,114,228,243,148,200,17,178,246,198,228,83]},"announce":[],"urlList":[]}}