{"title":"Sexy Brunette Emily Eats Banana And Sucks Dong Video","uid":14347379,"size":112842447,"categoryP":"porn","categoryS":"movie_clips","magnet":"?xt=urn:btih:6697d6b0fa24b9ab80924a727273944b79c19f78&amp;dn=Sexy+Brunette+Emily+Eats+Banana+And+Sucks+Dong+Video&amp;tr=udp%3A%2F%2Ftracker.leechers-paradise.org%3A6969&amp;tr=udp%3A%2F%2Fzer0day.ch%3A1337&amp;tr=udp%3A%2F%2Fopen.demonii.com%3A1337&amp;tr=udp%3A%2F%2Ftracker.coppersurfer.tk%3A6969&amp;tr=udp%3A%2F%2Fexodus.desync.com%3A6969","seeders":0,"leechers":1,"uploader":"demonoidt","files":5,"time":1460988453,"description":"Samples\r\n \nhttp://adultwallpapers.co.in/sexy-brunette-emily-eats-banana-and-sucks-dong-video/\r\n \nhttp://demonoid.co/2016/04/18/sexy-brunette-emily-eats-banana-and-sucks-dong-video/","torrent":{"xt":"urn:btih:6697d6b0fa24b9ab80924a727273944b79c19f78","amp;dn":"Sexy+Brunette+Emily+Eats+Banana+And+Sucks+Dong+Video","amp;tr":["udp%3A%2F%2Ftracker.leechers-paradise.org%3A6969","udp%3A%2F%2Fzer0day.ch%3A1337","udp%3A%2F%2Fopen.demonii.com%3A1337","udp%3A%2F%2Ftracker.coppersurfer.tk%3A6969","udp%3A%2F%2Fexodus.desync.com%3A6969"],"infoHash":"6697d6b0fa24b9ab80924a727273944b79c19f78","infoHashBuffer":{"type":"Buffer","data":[102,151,214,176,250,36,185,171,128,146,74,114,114,115,148,75,121,193,159,120]},"announce":[],"urlList":[]}}