{"title":"Bailey Takes A Young Man Home For A Nice Play Session Video","uid":14352537,"size":155306787,"categoryP":"porn","categoryS":"movie_clips","magnet":"?xt=urn:btih:7aa64eddf40690d6e020057af4c31bf95ae3640e&amp;dn=Bailey+Takes+A+Young+Man+Home+For+A+Nice+Play+Session+Video&amp;tr=udp%3A%2F%2Ftracker.leechers-paradise.org%3A6969&amp;tr=udp%3A%2F%2Fzer0day.ch%3A1337&amp;tr=udp%3A%2F%2Fopen.demonii.com%3A1337&amp;tr=udp%3A%2F%2Ftracker.coppersurfer.tk%3A6969&amp;tr=udp%3A%2F%2Fexodus.desync.com%3A6969","seeders":0,"leechers":0,"uploader":"demonoidt","files":5,"time":1461025949,"description":"Samples\r\n \nhttp://adultwallpapers.co.in/bailey-takes-a-young-man-home-for-a-nice-play-session-video/\r\n \nhttp://demonoid.co/2016/04/18/bailey-takes-a-young-man-home-for-a-nice-play-session-video/","torrent":{"xt":"urn:btih:7aa64eddf40690d6e020057af4c31bf95ae3640e","amp;dn":"Bailey+Takes+A+Young+Man+Home+For+A+Nice+Play+Session+Video","amp;tr":["udp%3A%2F%2Ftracker.leechers-paradise.org%3A6969","udp%3A%2F%2Fzer0day.ch%3A1337","udp%3A%2F%2Fopen.demonii.com%3A1337","udp%3A%2F%2Ftracker.coppersurfer.tk%3A6969","udp%3A%2F%2Fexodus.desync.com%3A6969"],"infoHash":"7aa64eddf40690d6e020057af4c31bf95ae3640e","infoHashBuffer":{"type":"Buffer","data":[122,166,78,221,244,6,144,214,224,32,5,122,244,195,27,249,90,227,100,14]},"announce":[],"urlList":[]}}