{"title":"Party.Over.Here.S01E04.HDTV.x264-Vip3r","uid":14159788,"size":137140202,"categoryP":"video","categoryS":"tv_shows","magnet":"?xt=urn:btih:822b488ae045afe39cb5566839f449213e292f64&amp;dn=Party.Over.Here.S01E04.HDTV.x264-Vip3r&amp;tr=udp%3A%2F%2Ftracker.leechers-paradise.org%3A6969&amp;tr=udp%3A%2F%2Fzer0day.ch%3A1337&amp;tr=udp%3A%2F%2Fopen.demonii.com%3A1337&amp;tr=udp%3A%2F%2Ftracker.coppersurfer.tk%3A6969&amp;tr=udp%3A%2F%2Fexodus.desync.com%3A6969","seeders":0,"leechers":2,"uploader":"BuSyVIP","files":1,"time":1459707660,"description":"Party.Over.Here.S01E04.HDTV.x264-Vip3r","torrent":{"xt":"urn:btih:822b488ae045afe39cb5566839f449213e292f64","amp;dn":"Party.Over.Here.S01E04.HDTV.x264-Vip3r","amp;tr":["udp%3A%2F%2Ftracker.leechers-paradise.org%3A6969","udp%3A%2F%2Fzer0day.ch%3A1337","udp%3A%2F%2Fopen.demonii.com%3A1337","udp%3A%2F%2Ftracker.coppersurfer.tk%3A6969","udp%3A%2F%2Fexodus.desync.com%3A6969"],"infoHash":"822b488ae045afe39cb5566839f449213e292f64","infoHashBuffer":{"type":"Buffer","data":[130,43,72,138,224,69,175,227,156,181,86,104,57,244,73,33,62,41,47,100]},"announce":[],"urlList":[]}}