{"title":"MilfsLikeItBig.Jewels.Jade.A.Dirty.Shower","uid":14518556,"size":229034056,"categoryP":"porn","categoryS":"movie_clips","magnet":"?xt=urn:btih:8bda91a7ecc74beae113b0cb40c8dc572808d532&amp;dn=MilfsLikeItBig.Jewels.Jade.A.Dirty.Shower&amp;tr=udp%3A%2F%2Ftracker.leechers-paradise.org%3A6969&amp;tr=udp%3A%2F%2Fzer0day.ch%3A1337&amp;tr=udp%3A%2F%2Fopen.demonii.com%3A1337&amp;tr=udp%3A%2F%2Ftracker.coppersurfer.tk%3A6969&amp;tr=udp%3A%2F%2Fexodus.desync.com%3A6969","seeders":0,"leechers":1,"uploader":"Piratepr0n","files":1,"time":1462356044,"description":"-------------------------------------------------------------------------------------\nName:\nMilfsLikeItBig.Jewels.Jade.A.Dirty.Shower\n-------------------------------------------------------------------------------------\nFile list:\nmlib.jewels.jade.bb072315.480p.1000.mp4 (218 MiB | 854x480 | 25min 35s | MPEG-4) \nhttp://imgfapper.com/img-5729ac235a7c9.html","torrent":{"xt":"urn:btih:8bda91a7ecc74beae113b0cb40c8dc572808d532","amp;dn":"MilfsLikeItBig.Jewels.Jade.A.Dirty.Shower","amp;tr":["udp%3A%2F%2Ftracker.leechers-paradise.org%3A6969","udp%3A%2F%2Fzer0day.ch%3A1337","udp%3A%2F%2Fopen.demonii.com%3A1337","udp%3A%2F%2Ftracker.coppersurfer.tk%3A6969","udp%3A%2F%2Fexodus.desync.com%3A6969"],"infoHash":"8bda91a7ecc74beae113b0cb40c8dc572808d532","infoHashBuffer":{"type":"Buffer","data":[139,218,145,167,236,199,75,234,225,19,176,203,64,200,220,87,40,8,213,50]},"announce":[],"urlList":[]}}