{"title":"Open Couples (2016) WEB-DL","uid":13575685,"size":1091446119,"categoryP":"porn","categoryS":"movies","magnet":"?xt=urn:btih:9eb0660dffed351966233c47878477267345f849&amp;dn=Open+Couples+%282016%29+WEB-DL+&amp;tr=udp%3A%2F%2Ftracker.leechers-paradise.org%3A6969&amp;tr=udp%3A%2F%2Fzer0day.ch%3A1337&amp;tr=udp%3A%2F%2Fopen.demonii.com%3A1337&amp;tr=udp%3A%2F%2Ftracker.coppersurfer.tk%3A6969&amp;tr=udp%3A%2F%2Fexodus.desync.com%3A6969","seeders":0,"leechers":0,"uploader":"ImgSnaps","files":4,"time":1455706085,"description":"Screenshots:\r\n \nhttp://imgsnaps.com/image/kGu\r\n \nhttp://imgsnaps.com/image/kGx\r\n \nhttp://imgsnaps.com/image/kGE\r\n \nhttp://imgsnaps.com/image/kGH\r\n \nhttp://imgsnaps.com/image/kGN\r\n\r\nDescription\r\nAnikka Albrite, Mia Malkova, Danny Mountain, Mick Blue\r\n\r\nCouples switch it up and get some serious action! Always swapping and never stopping, these couples are having the sexiest time of their lives!","torrent":{"xt":"urn:btih:9eb0660dffed351966233c47878477267345f849","amp;dn":"Open+Couples+%282016%29+WEB-DL+","amp;tr":["udp%3A%2F%2Ftracker.leechers-paradise.org%3A6969","udp%3A%2F%2Fzer0day.ch%3A1337","udp%3A%2F%2Fopen.demonii.com%3A1337","udp%3A%2F%2Ftracker.coppersurfer.tk%3A6969","udp%3A%2F%2Fexodus.desync.com%3A6969"],"infoHash":"9eb0660dffed351966233c47878477267345f849","infoHashBuffer":{"type":"Buffer","data":[158,176,102,13,255,237,53,25,102,35,60,71,135,132,119,38,115,69,248,73]},"announce":[],"urlList":[]}}