{"title":"Jiddu Krishnamurti PDF portugues","uid":14341538,"size":283677480,"categoryP":"other","categoryS":"e_books","magnet":"?xt=urn:btih:a8d45b809cc1fdb430bcc25391ad9323b782922a&amp;dn=Jiddu+Krishnamurti+PDF+portugues&amp;tr=udp%3A%2F%2Ftracker.leechers-paradise.org%3A6969&amp;tr=udp%3A%2F%2Fzer0day.ch%3A1337&amp;tr=udp%3A%2F%2Fopen.demonii.com%3A1337&amp;tr=udp%3A%2F%2Ftracker.coppersurfer.tk%3A6969&amp;tr=udp%3A%2F%2Fexodus.desync.com%3A6969","seeders":0,"leechers":0,"uploader":"prayuu","files":59,"time":1460763699,"description":"Jiddu Krishnamurti PT em PDF","torrent":{"xt":"urn:btih:a8d45b809cc1fdb430bcc25391ad9323b782922a","amp;dn":"Jiddu+Krishnamurti+PDF+portugues","amp;tr":["udp%3A%2F%2Ftracker.leechers-paradise.org%3A6969","udp%3A%2F%2Fzer0day.ch%3A1337","udp%3A%2F%2Fopen.demonii.com%3A1337","udp%3A%2F%2Ftracker.coppersurfer.tk%3A6969","udp%3A%2F%2Fexodus.desync.com%3A6969"],"infoHash":"a8d45b809cc1fdb430bcc25391ad9323b782922a","infoHashBuffer":{"type":"Buffer","data":[168,212,91,128,156,193,253,180,48,188,194,83,145,173,147,35,183,130,146,42]},"announce":[],"urlList":[]}}