{"title":"MommyGotBoobs - Alexis Fawx (The Naked Mom) NEW 26 April 2016","uid":14438677,"size":325452687,"categoryP":"porn","categoryS":"movie_clips","magnet":"?xt=urn:btih:a91ff3b050205a1bd1fd751f0ec5b4b9720fc7aa&amp;dn=MommyGotBoobs+-+Alexis+Fawx+%28The+Naked+Mom%29+NEW+26+April+2016&amp;tr=udp%3A%2F%2Ftracker.leechers-paradise.org%3A6969&amp;tr=udp%3A%2F%2Fzer0day.ch%3A1337&amp;tr=udp%3A%2F%2Fopen.demonii.com%3A1337&amp;tr=udp%3A%2F%2Ftracker.coppersurfer.tk%3A6969&amp;tr=udp%3A%2F%2Fexodus.desync.com%3A6969","seeders":0,"leechers":1,"uploader":"xxxlavalxxx","files":2,"time":1461657522,"description":"Alexis is a free spirit hippie sort who enjoys doing her housework in the nude. Johnny is her sonâ™s pervy friend who drops by and is surprised to find Alexis naked. After creeping on her and checking her out, Johnny makes his move and the two fuck.\r\nCategories\r\nMILF Blonde Mom Big Tits Big Tits Worship\r\n \nhttp://imgdone.com/viewer.php?file=39254445508149519006.jpg\r\n \nhttp://imgdone.com/viewer.php?file=21117021490741790694.jpg","torrent":{"xt":"urn:btih:a91ff3b050205a1bd1fd751f0ec5b4b9720fc7aa","amp;dn":"MommyGotBoobs+-+Alexis+Fawx+%28The+Naked+Mom%29+NEW+26+April+2016","amp;tr":["udp%3A%2F%2Ftracker.leechers-paradise.org%3A6969","udp%3A%2F%2Fzer0day.ch%3A1337","udp%3A%2F%2Fopen.demonii.com%3A1337","udp%3A%2F%2Ftracker.coppersurfer.tk%3A6969","udp%3A%2F%2Fexodus.desync.com%3A6969"],"infoHash":"a91ff3b050205a1bd1fd751f0ec5b4b9720fc7aa","infoHashBuffer":{"type":"Buffer","data":[169,31,243,176,80,32,90,27,209,253,117,31,14,197,180,185,114,15,199,170]},"announce":[],"urlList":[]}}