{"title":"GroupSexGames Heart Lines XXX 16.03.11","uid":14333543,"size":1783436966,"categoryP":"porn","categoryS":"movie_clips","magnet":"?xt=urn:btih:aeba2cf6040bea5e84b9be3cb4b2ba39d1586f3a&amp;dn=GroupSexGames+Heart+Lines+XXX+16.03.11&amp;tr=udp%3A%2F%2Ftracker.leechers-paradise.org%3A6969&amp;tr=udp%3A%2F%2Fzer0day.ch%3A1337&amp;tr=udp%3A%2F%2Fopen.demonii.com%3A1337&amp;tr=udp%3A%2F%2Ftracker.coppersurfer.tk%3A6969&amp;tr=udp%3A%2F%2Fexodus.desync.com%3A6969","seeders":0,"leechers":2,"uploader":"thfatboys","files":1,"time":1460691588,"description":"Screens: \nhttp://imgpeak.com/img-571003ddb9f71.html","torrent":{"xt":"urn:btih:aeba2cf6040bea5e84b9be3cb4b2ba39d1586f3a","amp;dn":"GroupSexGames+Heart+Lines+XXX+16.03.11","amp;tr":["udp%3A%2F%2Ftracker.leechers-paradise.org%3A6969","udp%3A%2F%2Fzer0day.ch%3A1337","udp%3A%2F%2Fopen.demonii.com%3A1337","udp%3A%2F%2Ftracker.coppersurfer.tk%3A6969","udp%3A%2F%2Fexodus.desync.com%3A6969"],"infoHash":"aeba2cf6040bea5e84b9be3cb4b2ba39d1586f3a","infoHashBuffer":{"type":"Buffer","data":[174,186,44,246,4,11,234,94,132,185,190,60,180,178,186,57,209,88,111,58]},"announce":[],"urlList":[]}}