{"title":"Mr Right 2016 V2 HDRip XviD AC3-EVO","uid":14237693,"size":1490259662,"categoryP":"video","categoryS":"movies","magnet":"?xt=urn:btih:b6c9c9e10aad1cd30b7e6eff673fde127f3897a9&amp;dn=Mr+Right+2016+V2+HDRip+XviD+AC3-EVO&amp;tr=udp%3A%2F%2Ftracker.leechers-paradise.org%3A6969&amp;tr=udp%3A%2F%2Fzer0day.ch%3A1337&amp;tr=udp%3A%2F%2Fopen.demonii.com%3A1337&amp;tr=udp%3A%2F%2Ftracker.coppersurfer.tk%3A6969&amp;tr=udp%3A%2F%2Fexodus.desync.com%3A6969","seeders":0,"leechers":1,"uploader":"hotpena","files":4,"time":1460109456,"description":"SCREENS:  \nhttp://icezap.com/img-570764097aac7.html\n \nhttp://icezap.com/img-570764097cb4c.html\n \nhttp://icezap.com/img-570764097e624.html\n\n\nDOWNLOAD AND ENJOY. \n\n KEEP IT FOR LONG SEEDING TO HELP OTHERS \n\n \n Thanks to : EVO\n Movie Share","torrent":{"xt":"urn:btih:b6c9c9e10aad1cd30b7e6eff673fde127f3897a9","amp;dn":"Mr+Right+2016+V2+HDRip+XviD+AC3-EVO","amp;tr":["udp%3A%2F%2Ftracker.leechers-paradise.org%3A6969","udp%3A%2F%2Fzer0day.ch%3A1337","udp%3A%2F%2Fopen.demonii.com%3A1337","udp%3A%2F%2Ftracker.coppersurfer.tk%3A6969","udp%3A%2F%2Fexodus.desync.com%3A6969"],"infoHash":"b6c9c9e10aad1cd30b7e6eff673fde127f3897a9","infoHashBuffer":{"type":"Buffer","data":[182,201,201,225,10,173,28,211,11,126,110,255,103,63,222,18,127,56,151,169]},"announce":[],"urlList":[]}}