{"title":"Joone Productions - Miami MILFs 5 - SS - 2016","uid":13910633,"size":1247293943,"categoryP":"porn","categoryS":"movies","magnet":"?xt=urn:btih:b773413ab7af87980c37a6c643e3066e0a1d4bc2&amp;dn=Joone+Productions+-+Miami+MILFs+5+-+SS+-+2016&amp;tr=udp%3A%2F%2Ftracker.leechers-paradise.org%3A6969&amp;tr=udp%3A%2F%2Fzer0day.ch%3A1337&amp;tr=udp%3A%2F%2Fopen.demonii.com%3A1337&amp;tr=udp%3A%2F%2Ftracker.coppersurfer.tk%3A6969&amp;tr=udp%3A%2F%2Fexodus.desync.com%3A6969","seeders":0,"leechers":0,"uploader":"hotpena","files":4,"time":1458298063,"description":"SCREENS:  \nhttp://inffa.com/img-56ebce4af3032.html\n \nhttp://inffa.com/img-56ebce4b0438f.html\n \nhttp://inffa.com/img-56ebce4b0873f.html\n\n\nDOWNLOAD AND ENJOY. \n\n KEEP IT FOR LONG SEEDING TO HELP OTHERS \n\n \n Thanks to  encoder \n Movie Share","torrent":{"xt":"urn:btih:b773413ab7af87980c37a6c643e3066e0a1d4bc2","amp;dn":"Joone+Productions+-+Miami+MILFs+5+-+SS+-+2016","amp;tr":["udp%3A%2F%2Ftracker.leechers-paradise.org%3A6969","udp%3A%2F%2Fzer0day.ch%3A1337","udp%3A%2F%2Fopen.demonii.com%3A1337","udp%3A%2F%2Ftracker.coppersurfer.tk%3A6969","udp%3A%2F%2Fexodus.desync.com%3A6969"],"infoHash":"b773413ab7af87980c37a6c643e3066e0a1d4bc2","infoHashBuffer":{"type":"Buffer","data":[183,115,65,58,183,175,135,152,12,55,166,198,67,227,6,110,10,29,75,194]},"announce":[],"urlList":[]}}