{"title":"#_DANDY480","uid":13911923,"size":1977800745,"categoryP":"porn","categoryS":"movie_clips","magnet":"?xt=urn:btih:be7c5403a7ec93824c9df659917e2d4d91db2c49&amp;dn=%23_DANDY480&amp;tr=udp%3A%2F%2Ftracker.leechers-paradise.org%3A6969&amp;tr=udp%3A%2F%2Fzer0day.ch%3A1337&amp;tr=udp%3A%2F%2Fopen.demonii.com%3A1337&amp;tr=udp%3A%2F%2Ftracker.coppersurfer.tk%3A6969&amp;tr=udp%3A%2F%2Fexodus.desync.com%3A6969","seeders":0,"leechers":0,"uploader":"Piratepr0n","files":1,"time":1458306935,"description":"-------------------------------------------------------------------------------------\nName:\n#_DANDY480\n-------------------------------------------------------------------------------------\nFile list:\nDANDY480.mp4 (1.84 GiB | 856x480 | 3h 19min | MPEG-4) \nhttp://imgfapper.com/img-56ebf15edc9ea.html","torrent":{"xt":"urn:btih:be7c5403a7ec93824c9df659917e2d4d91db2c49","amp;dn":"%23_DANDY480","amp;tr":["udp%3A%2F%2Ftracker.leechers-paradise.org%3A6969","udp%3A%2F%2Fzer0day.ch%3A1337","udp%3A%2F%2Fopen.demonii.com%3A1337","udp%3A%2F%2Ftracker.coppersurfer.tk%3A6969","udp%3A%2F%2Fexodus.desync.com%3A6969"],"infoHash":"be7c5403a7ec93824c9df659917e2d4d91db2c49","infoHashBuffer":{"type":"Buffer","data":[190,124,84,3,167,236,147,130,76,157,246,89,145,126,45,77,145,219,44,73]},"announce":[],"urlList":[]}}