{"title":"Big Titty White Girls 2","uid":14358384,"size":1452634112,"categoryP":"porn","categoryS":"movies","magnet":"?xt=urn:btih:bff8cd0ab9e1b7f19f16402398f390c8f4b57062&amp;dn=Big+Titty+White+Girls+2&amp;tr=udp%3A%2F%2Ftracker.leechers-paradise.org%3A6969&amp;tr=udp%3A%2F%2Fzer0day.ch%3A1337&amp;tr=udp%3A%2F%2Fopen.demonii.com%3A1337&amp;tr=udp%3A%2F%2Ftracker.coppersurfer.tk%3A6969&amp;tr=udp%3A%2F%2Fexodus.desync.com%3A6969","seeders":0,"leechers":1,"uploader":"hotpena","files":2,"time":1461074551,"description":"DOWNLOAD AND ENJOY. \n\n KEEP IT FOR LONG SEEDING TO HELP OTHERS \n\n \n Thanks to  encoder \n Movie Share","torrent":{"xt":"urn:btih:bff8cd0ab9e1b7f19f16402398f390c8f4b57062","amp;dn":"Big+Titty+White+Girls+2","amp;tr":["udp%3A%2F%2Ftracker.leechers-paradise.org%3A6969","udp%3A%2F%2Fzer0day.ch%3A1337","udp%3A%2F%2Fopen.demonii.com%3A1337","udp%3A%2F%2Ftracker.coppersurfer.tk%3A6969","udp%3A%2F%2Fexodus.desync.com%3A6969"],"infoHash":"bff8cd0ab9e1b7f19f16402398f390c8f4b57062","infoHashBuffer":{"type":"Buffer","data":[191,248,205,10,185,225,183,241,159,22,64,35,152,243,144,200,244,181,112,98]},"announce":[],"urlList":[]}}