{"title":"Czechav - CzechCasting - Barbora [1080p].mp4","uid":14157831,"size":619671237,"categoryP":"porn","categoryS":"hd___movies","magnet":"?xt=urn:btih:c15f9f6c8758c3a534b6341ff1cf395e43aabf3f&amp;dn=Czechav+-+CzechCasting+-+Barbora+%5B1080p%5D.mp4&amp;tr=udp%3A%2F%2Ftracker.leechers-paradise.org%3A6969&amp;tr=udp%3A%2F%2Fzer0day.ch%3A1337&amp;tr=udp%3A%2F%2Fopen.demonii.com%3A1337&amp;tr=udp%3A%2F%2Ftracker.coppersurfer.tk%3A6969&amp;tr=udp%3A%2F%2Fexodus.desync.com%3A6969","seeders":0,"leechers":0,"uploader":"1.No.1","files":1,"time":1459683401,"description":"Czechav - CzechCasting - Barbora [1080p].mp4\r\n\r\n2016, Amateur, Teen, Casting, Posing, Talking, Oil, HD, XXX, Adult\r\n\r\n590.96 MB \r\n\r\nScreens\r\n \nhttp://imgcentral.com/viewer.php?file=47213674295829283216.jpg\r\n \nhttp://imgcentral.com/viewer.php?file=91583544691035209859.jpg\r\n \nhttp://imgcentral.com/viewer.php?file=52010973886609436158.jpg\r\n \nhttp://imgcentral.com/viewer.php?file=57707329730848075790.jpg","torrent":{"xt":"urn:btih:c15f9f6c8758c3a534b6341ff1cf395e43aabf3f","amp;dn":"Czechav+-+CzechCasting+-+Barbora+%5B1080p%5D.mp4","amp;tr":["udp%3A%2F%2Ftracker.leechers-paradise.org%3A6969","udp%3A%2F%2Fzer0day.ch%3A1337","udp%3A%2F%2Fopen.demonii.com%3A1337","udp%3A%2F%2Ftracker.coppersurfer.tk%3A6969","udp%3A%2F%2Fexodus.desync.com%3A6969"],"infoHash":"c15f9f6c8758c3a534b6341ff1cf395e43aabf3f","infoHashBuffer":{"type":"Buffer","data":[193,95,159,108,135,88,195,165,52,182,52,31,241,207,57,94,67,170,191,63]},"announce":[],"urlList":[]}}