{"title":"ATKGirlfriends Scarlett Sage XXX 1080p 16.04.14","uid":14333324,"size":1183446502,"categoryP":"porn","categoryS":"hd___movies","magnet":"?xt=urn:btih:c231a0f32d1d8597b9163eff25df8b7cfec84d2e&amp;dn=ATKGirlfriends+Scarlett+Sage+XXX+1080p+16.04.14&amp;tr=udp%3A%2F%2Ftracker.leechers-paradise.org%3A6969&amp;tr=udp%3A%2F%2Fzer0day.ch%3A1337&amp;tr=udp%3A%2F%2Fopen.demonii.com%3A1337&amp;tr=udp%3A%2F%2Ftracker.coppersurfer.tk%3A6969&amp;tr=udp%3A%2F%2Fexodus.desync.com%3A6969","seeders":0,"leechers":1,"uploader":"thfatboys","files":1,"time":1460690957,"description":"Screens: \nhttp://imgpeak.com/img-571003cd38866.html","torrent":{"xt":"urn:btih:c231a0f32d1d8597b9163eff25df8b7cfec84d2e","amp;dn":"ATKGirlfriends+Scarlett+Sage+XXX+1080p+16.04.14","amp;tr":["udp%3A%2F%2Ftracker.leechers-paradise.org%3A6969","udp%3A%2F%2Fzer0day.ch%3A1337","udp%3A%2F%2Fopen.demonii.com%3A1337","udp%3A%2F%2Ftracker.coppersurfer.tk%3A6969","udp%3A%2F%2Fexodus.desync.com%3A6969"],"infoHash":"c231a0f32d1d8597b9163eff25df8b7cfec84d2e","infoHashBuffer":{"type":"Buffer","data":[194,49,160,243,45,29,133,151,185,22,62,255,37,223,139,124,254,200,77,46]},"announce":[],"urlList":[]}}