{"title":"The Weekly Charlie Pickering s02e14 Finale 360p MPup","uid":14543807,"size":154680359,"categoryP":"video","categoryS":"tv_shows","magnet":"?xt=urn:btih:c59e1100f5e90c26d423126427cf52fa126c1d2a&amp;dn=The+Weekly+Charlie+Pickering+s02e14+Finale+360p+MPup&amp;tr=udp%3A%2F%2Ftracker.leechers-paradise.org%3A6969&amp;tr=udp%3A%2F%2Fzer0day.ch%3A1337&amp;tr=udp%3A%2F%2Fopen.demonii.com%3A1337&amp;tr=udp%3A%2F%2Ftracker.coppersurfer.tk%3A6969&amp;tr=udp%3A%2F%2Fexodus.desync.com%3A6969","seeders":0,"leechers":0,"uploader":"makinapufterpup","files":1,"time":1462553452,"description":"The.Weekly.with.Charlie.Pickering.S02E14.Finale.360p.LDTV.WEBRIP.[MPup]\r\nLow-Definition Television (LDTV) ABC iview WEBRIP: 640x360\r\n\r\nFormat: MPEG-4\r\nSize: 640x360\r\nFrameRate: 25.000 fps\r\nAudioCodec: AAC\r\nChannels: 2 channels\r\nSamplingRate: 44.1 KHz\r\n\r\nFor the final time this season, Charlie Pickering, Tom Gleeson &amp; Kitty Flanagan put the sense back into the nonsense of the news world. #TheWeekly (Final)","torrent":{"xt":"urn:btih:c59e1100f5e90c26d423126427cf52fa126c1d2a","amp;dn":"The+Weekly+Charlie+Pickering+s02e14+Finale+360p+MPup","amp;tr":["udp%3A%2F%2Ftracker.leechers-paradise.org%3A6969","udp%3A%2F%2Fzer0day.ch%3A1337","udp%3A%2F%2Fopen.demonii.com%3A1337","udp%3A%2F%2Ftracker.coppersurfer.tk%3A6969","udp%3A%2F%2Fexodus.desync.com%3A6969"],"infoHash":"c59e1100f5e90c26d423126427cf52fa126c1d2a","infoHashBuffer":{"type":"Buffer","data":[197,158,17,0,245,233,12,38,212,35,18,100,39,207,82,250,18,108,29,42]},"announce":[],"urlList":[]}}