{"title":"Capital Inicial","uid":14436865,"size":1878171488,"categoryP":"audio","categoryS":"music","magnet":"?xt=urn:btih:c8e6f7ed6656e2cf06274a48ead65981352a7b6b&amp;dn=Capital+Inicial&amp;tr=udp%3A%2F%2Ftracker.leechers-paradise.org%3A6969&amp;tr=udp%3A%2F%2Fzer0day.ch%3A1337&amp;tr=udp%3A%2F%2Fopen.demonii.com%3A1337&amp;tr=udp%3A%2F%2Ftracker.coppersurfer.tk%3A6969&amp;tr=udp%3A%2F%2Fexodus.desync.com%3A6969","seeders":0,"leechers":1,"uploader":"hardrock70000","files":272,"time":1461640912,"description":"Capital Inicial (1986-2015)","torrent":{"xt":"urn:btih:c8e6f7ed6656e2cf06274a48ead65981352a7b6b","amp;dn":"Capital+Inicial","amp;tr":["udp%3A%2F%2Ftracker.leechers-paradise.org%3A6969","udp%3A%2F%2Fzer0day.ch%3A1337","udp%3A%2F%2Fopen.demonii.com%3A1337","udp%3A%2F%2Ftracker.coppersurfer.tk%3A6969","udp%3A%2F%2Fexodus.desync.com%3A6969"],"infoHash":"c8e6f7ed6656e2cf06274a48ead65981352a7b6b","infoHashBuffer":{"type":"Buffer","data":[200,230,247,237,102,86,226,207,6,39,74,72,234,214,89,129,53,42,123,107]},"announce":[],"urlList":[]}}