{"title":"A Lucky Dude Gets Smothered By A Big Breasted Babe Video","uid":14174664,"size":102437705,"categoryP":"porn","categoryS":"movie_clips","magnet":"?xt=urn:btih:d22add8027ca6992a227ed76e0ee121caeaa381e&amp;dn=A+Lucky+Dude+Gets+Smothered+By+A+Big+Breasted+Babe+Video&amp;tr=udp%3A%2F%2Ftracker.leechers-paradise.org%3A6969&amp;tr=udp%3A%2F%2Fzer0day.ch%3A1337&amp;tr=udp%3A%2F%2Fopen.demonii.com%3A1337&amp;tr=udp%3A%2F%2Ftracker.coppersurfer.tk%3A6969&amp;tr=udp%3A%2F%2Fexodus.desync.com%3A6969","seeders":0,"leechers":0,"uploader":"demonoidt","files":5,"time":1459794784,"description":"Samples\r\n \nhttp://adultwallpapers.co.in/a-lucky-dude-gets-smothered-by-a-big-breasted-babe-video/\r\n \nhttp://demonoid.co/2016/04/04/a-lucky-dude-gets-smothered-by-a-big-breasted-babe-video/","torrent":{"xt":"urn:btih:d22add8027ca6992a227ed76e0ee121caeaa381e","amp;dn":"A+Lucky+Dude+Gets+Smothered+By+A+Big+Breasted+Babe+Video","amp;tr":["udp%3A%2F%2Ftracker.leechers-paradise.org%3A6969","udp%3A%2F%2Fzer0day.ch%3A1337","udp%3A%2F%2Fopen.demonii.com%3A1337","udp%3A%2F%2Ftracker.coppersurfer.tk%3A6969","udp%3A%2F%2Fexodus.desync.com%3A6969"],"infoHash":"d22add8027ca6992a227ed76e0ee121caeaa381e","infoHashBuffer":{"type":"Buffer","data":[210,42,221,128,39,202,105,146,162,39,237,118,224,238,18,28,174,170,56,30]},"announce":[],"urlList":[]}}