{"title":"cock filled pussy and ass Video","uid":14239084,"size":181019433,"categoryP":"porn","categoryS":"movie_clips","magnet":"?xt=urn:btih:d8e7c441268bf96d242a5b3da9e84d4c4f4731c5&amp;dn=cock+filled+pussy+and+ass+Video&amp;tr=udp%3A%2F%2Ftracker.leechers-paradise.org%3A6969&amp;tr=udp%3A%2F%2Fzer0day.ch%3A1337&amp;tr=udp%3A%2F%2Fopen.demonii.com%3A1337&amp;tr=udp%3A%2F%2Ftracker.coppersurfer.tk%3A6969&amp;tr=udp%3A%2F%2Fexodus.desync.com%3A6969","seeders":0,"leechers":0,"uploader":"demonoidt","files":5,"time":1460124984,"description":"Samples\r\n \nhttp://demonoid.co/2016/04/08/cock-filled-pussy-and-ass-video/\r\n \nhttp://adultwallpapers.co.in/cock-filled-pussy-and-ass-video/","torrent":{"xt":"urn:btih:d8e7c441268bf96d242a5b3da9e84d4c4f4731c5","amp;dn":"cock+filled+pussy+and+ass+Video","amp;tr":["udp%3A%2F%2Ftracker.leechers-paradise.org%3A6969","udp%3A%2F%2Fzer0day.ch%3A1337","udp%3A%2F%2Fopen.demonii.com%3A1337","udp%3A%2F%2Ftracker.coppersurfer.tk%3A6969","udp%3A%2F%2Fexodus.desync.com%3A6969"],"infoHash":"d8e7c441268bf96d242a5b3da9e84d4c4f4731c5","infoHashBuffer":{"type":"Buffer","data":[216,231,196,65,38,139,249,109,36,42,91,61,169,232,77,76,79,71,49,197]},"announce":[],"urlList":[]}}