{"title":"CumPerfection Brooklyn Blue Rude Selfies XXX 16.04.21","uid":14391097,"size":121201686,"categoryP":"porn","categoryS":"movie_clips","magnet":"?xt=urn:btih:e7c14e25ce78be8f09f0b930979889fc0c20ce47&amp;dn=CumPerfection+Brooklyn+Blue+Rude+Selfies+XXX+16.04.21&amp;tr=udp%3A%2F%2Ftracker.leechers-paradise.org%3A6969&amp;tr=udp%3A%2F%2Fzer0day.ch%3A1337&amp;tr=udp%3A%2F%2Fopen.demonii.com%3A1337&amp;tr=udp%3A%2F%2Ftracker.coppersurfer.tk%3A6969&amp;tr=udp%3A%2F%2Fexodus.desync.com%3A6969","seeders":0,"leechers":1,"uploader":"thfatboys","files":1,"time":1461302447,"description":"Screens: \nhttp://imgpeak.com/img-57193cf78f01b.html","torrent":{"xt":"urn:btih:e7c14e25ce78be8f09f0b930979889fc0c20ce47","amp;dn":"CumPerfection+Brooklyn+Blue+Rude+Selfies+XXX+16.04.21","amp;tr":["udp%3A%2F%2Ftracker.leechers-paradise.org%3A6969","udp%3A%2F%2Fzer0day.ch%3A1337","udp%3A%2F%2Fopen.demonii.com%3A1337","udp%3A%2F%2Ftracker.coppersurfer.tk%3A6969","udp%3A%2F%2Fexodus.desync.com%3A6969"],"infoHash":"e7c14e25ce78be8f09f0b930979889fc0c20ce47","infoHashBuffer":{"type":"Buffer","data":[231,193,78,37,206,120,190,143,9,240,185,48,151,152,137,252,12,32,206,71]},"announce":[],"urlList":[]}}