{"title":"Oblivion FCOM","uid":14565919,"size":2069357094,"categoryP":"games","categoryS":"pc","magnet":"?xt=urn:btih:eacd9a832cd555c809781649e55562fdde5bae76&amp;dn=Oblivion+FCOM&amp;tr=udp%3A%2F%2Ftracker.leechers-paradise.org%3A6969&amp;tr=udp%3A%2F%2Fzer0day.ch%3A1337&amp;tr=udp%3A%2F%2Fopen.demonii.com%3A1337&amp;tr=udp%3A%2F%2Ftracker.coppersurfer.tk%3A6969&amp;tr=udp%3A%2F%2Fexodus.desync.com%3A6969","seeders":0,"leechers":0,"uploader":"asleikdpd","files":32,"time":1462760379,"description":"All files needed for FCOM instalation.\r\n\r\nOblivion not included.\r\n\r\nI've just made the package, just grouped all files togheter.\r\n\r\nPDF Manual included.\r\n\r\nSeed and enjoy","torrent":{"xt":"urn:btih:eacd9a832cd555c809781649e55562fdde5bae76","amp;dn":"Oblivion+FCOM","amp;tr":["udp%3A%2F%2Ftracker.leechers-paradise.org%3A6969","udp%3A%2F%2Fzer0day.ch%3A1337","udp%3A%2F%2Fopen.demonii.com%3A1337","udp%3A%2F%2Ftracker.coppersurfer.tk%3A6969","udp%3A%2F%2Fexodus.desync.com%3A6969"],"infoHash":"eacd9a832cd555c809781649e55562fdde5bae76","infoHashBuffer":{"type":"Buffer","data":[234,205,154,131,44,213,85,200,9,120,22,73,229,85,98,253,222,91,174,118]},"announce":[],"urlList":[]}}