{"title":"Saving.God.2008.1080p.BluRay.x264.DTS-FGT","uid":14271288,"size":7901685100,"categoryP":"video","categoryS":"hd___movies","magnet":"?xt=urn:btih:efa03bf898d807295e234a23632bc4518f08a222&amp;dn=Saving.God.2008.1080p.BluRay.x264.DTS-FGT&amp;tr=udp%3A%2F%2Ftracker.leechers-paradise.org%3A6969&amp;tr=udp%3A%2F%2Fzer0day.ch%3A1337&amp;tr=udp%3A%2F%2Fopen.demonii.com%3A1337&amp;tr=udp%3A%2F%2Ftracker.coppersurfer.tk%3A6969&amp;tr=udp%3A%2F%2Fexodus.desync.com%3A6969","seeders":0,"leechers":1,"uploader":"makintos13","files":3,"time":1460313782,"description":"Saving.God.2008.1080p.BluRay.x264.DTS-FGT\r\n\r\nscreen:\r\n \nhttp://imgmak.com/KX7\r\n \nhttp://imgmak.com/KXk\r\n \nhttp://imgmak.com/KXm\r\n\r\nVideo\r\nID                                       : 1\r\nFormat                                   : AVC\r\nFormat/Info                              : Advanced Video Codec\r\nFormat profile                           :   \r\nFormat settings, CABAC                   : Yes\r\nFormat settings, ReFrames                : 4 frames\r\nCodec ID                                 : V_MPEG4/ISO/AVC\r\nDuration                                 : 1h 40mn\r\nBit rate                                 : 8 725 Kbps\r\n\r\nWidth                                    : 1 920 pixels\r\n\r\nHeight                                   : 1 080 pixels\r\n\r\nDisplay aspect ratio                     : 16:9","torrent":{"xt":"urn:btih:efa03bf898d807295e234a23632bc4518f08a222","amp;dn":"Saving.God.2008.1080p.BluRay.x264.DTS-FGT","amp;tr":["udp%3A%2F%2Ftracker.leechers-paradise.org%3A6969","udp%3A%2F%2Fzer0day.ch%3A1337","udp%3A%2F%2Fopen.demonii.com%3A1337","udp%3A%2F%2Ftracker.coppersurfer.tk%3A6969","udp%3A%2F%2Fexodus.desync.com%3A6969"],"infoHash":"efa03bf898d807295e234a23632bc4518f08a222","infoHashBuffer":{"type":"Buffer","data":[239,160,59,248,152,216,7,41,94,35,74,35,99,43,196,81,143,8,162,34]},"announce":[],"urlList":[]}}