{"title":"[MomsTeachSex.com  NubilesNetwork.com] Jessa Rhodes, Lucy Doll (","uid":14371106,"size":551146538,"categoryP":"porn","categoryS":"movie_clips","magnet":"?xt=urn:btih:fba2906c6c7977637d034a37a59ebef7cc963853&amp;dn=%5BMomsTeachSex.com++NubilesNetwork.com%5D+Jessa+Rhodes%2C+Lucy+Doll+%28&amp;tr=udp%3A%2F%2Ftracker.leechers-paradise.org%3A6969&amp;tr=udp%3A%2F%2Fzer0day.ch%3A1337&amp;tr=udp%3A%2F%2Fopen.demonii.com%3A1337&amp;tr=udp%3A%2F%2Ftracker.coppersurfer.tk%3A6969&amp;tr=udp%3A%2F%2Fexodus.desync.com%3A6969","seeders":0,"leechers":0,"uploader":"Piratepr0n","files":1,"time":1461160944,"description":"-------------------------------------------------------------------------------------\nName:\n[MomsTeachSex.com  NubilesNetwork.com] Jessa Rhodes, Lucy Doll (Stepmom Steps In) (18.04.16)\n-------------------------------------------------------------------------------------\nFile list:\n[MomsTeachSex] Jessa Rhodes, Lucy Doll (Stepmom Steps In - 18.04.16) rq (540p).mp4 (526 MiB | 960x540 | 30min 33s | MPEG-4) \nhttp://imgfapper.com/img-57176fc5229c3.html","torrent":{"xt":"urn:btih:fba2906c6c7977637d034a37a59ebef7cc963853","amp;dn":"%5BMomsTeachSex.com++NubilesNetwork.com%5D+Jessa+Rhodes%2C+Lucy+Doll+%28","amp;tr":["udp%3A%2F%2Ftracker.leechers-paradise.org%3A6969","udp%3A%2F%2Fzer0day.ch%3A1337","udp%3A%2F%2Fopen.demonii.com%3A1337","udp%3A%2F%2Ftracker.coppersurfer.tk%3A6969","udp%3A%2F%2Fexodus.desync.com%3A6969"],"infoHash":"fba2906c6c7977637d034a37a59ebef7cc963853","infoHashBuffer":{"type":"Buffer","data":[251,162,144,108,108,121,119,99,125,3,74,55,165,158,190,247,204,150,56,83]},"announce":[],"urlList":[]}}